setup.cfg
setup.py
django_grapevine.egg-info/PKG-INFO
django_grapevine.egg-info/SOURCES.txt
django_grapevine.egg-info/dependency_links.txt
django_grapevine.egg-info/pbr.json
django_grapevine.egg-info/requires.txt
django_grapevine.egg-info/top_level.txt
grapevine/__init__.py
grapevine/decorators.py
grapevine/engines.py
grapevine/generics.py
grapevine/managers.py
grapevine/mixins.py
grapevine/querysets.py
grapevine/sender.py
grapevine/settings.py
grapevine/tasks.py
grapevine/urls.py
grapevine/utils.py
grapevine/widgets.py
grapevine/admin/__init__.py
grapevine/admin/base.py
grapevine/emails/__init__.py
grapevine/emails/admin.py
grapevine/emails/apps.py
grapevine/emails/filters.py
grapevine/emails/jobs.py
grapevine/emails/managers.py
grapevine/emails/models.py
grapevine/emails/urls.py
grapevine/emails/utils.py
grapevine/emails/views.py
grapevine/emails/backends/__init__.py
grapevine/emails/backends/base.py
grapevine/emails/backends/mailgun.py
grapevine/emails/backends/sendgrid_driver.py
grapevine/emails/migrations/0001_initial.py
grapevine/emails/migrations/0002_meta_changes.py
grapevine/emails/migrations/0003_email_defaults.py
grapevine/emails/migrations/0004_blankable_fields.py
grapevine/emails/migrations/__init__.py
grapevine/emails/south_migrations/0001_initial.py
grapevine/emails/south_migrations/__init__.py
grapevine/emails/templates/admin/change_emailable_form.html
grapevine/emails/templates/admin/send_real.html
grapevine/emails/templates/admin/send_test.html
grapevine/emails/templates/admin/suit_change_emailable_form.html
grapevine/management/__init__.py
grapevine/management/commands/__init__.py
grapevine/management/commands/send_messages.py
grapevine/migrations/0001_initial.py
grapevine/migrations/__init__.py
grapevine/models/__init__.py
grapevine/models/base.py
grapevine/south_migrations/0001_initial.py
grapevine/south_migrations/__init__.py
grapevine/templates/.DS_Store
grapevine/templates/admin/.DS_Store
grapevine/templates/admin/change_sendable_form.html
grapevine/templates/admin/grapevine_change_form.html
grapevine/templates/email/internal_base.html
grapevine/templates/email/minty_original.html