Metadata-Version: 1.1
Name: django-grapevine
Version: 0.4.0
Summary: A comprehensive email tool for Django
Home-page: https://github.com/craiglabenz/django-grapevine
Author: Craig Labenz
Author-email: craig.labenz@gmail.com
License: MIT
Download-URL: https://github.com/craiglabenz/django-grapevine/tarball/0.4.0
Keywords: django,email,sending,tracking
Platform: UNKNOWN
Classifier: Framework :: Django
Classifier: Intended Audience :: Developers
Classifier: Programming Language :: Python
